[
    {"card": "The Fool", "upright": "Beginnings", "reversed": "Recklessness"},
    {"card": "The Magician", "upright": "Power", "reversed": "Manipulation"},
    {"card": "The High Priestess", "upright": "Intuition", "reversed": "Secrets"},
    {"card": "The Empress", "upright": "Fruitfulness", "reversed": "Dependency"},
    {"card": "The Emperor", "upright": "Authority", "reversed": "Tyranny"},
    {"card": "The Hierophant", "upright": "Tradition", "reversed": "Rebellion"},
    {"card": "The Lovers", "upright": "Union", "reversed": "Disharmony"},
    {"card": "The Chariot", "upright": "Victory", "reversed": "Challenge"},
    {"card": "Strength", "upright": "Courage", "reversed": "Self-Doubt"},
    {"card": "The Hermit", "upright": "Introspection", "reversed": "Withdrawal"},
    {"card": "Wheel of Fortune", "upright": "Luck", "reversed": "Misfortune"},
    {"card": "Justice", "upright": "Fairness", "reversed": "Iniquity"},
    {"card": "The Hanged Man", "upright": "Surrender", "reversed": "Resistance"},
    {"card": "Death", "upright": "Change", "reversed": "Stagnation"},
    {"card": "Temperance", "upright": "Moderation", "reversed": "Excess"},
    {"card": "The Devil", "upright": "Bondage", "reversed": "Freedom"},
    {"card": "The Tower", "upright": "Upheaval", "reversed": "Avoidance"},
    {"card": "The Star", "upright": "Hope", "reversed": "Despair"},
    {"card": "The Moon", "upright": "Illusion", "reversed": "Confusion"},
    {"card": "The Sun", "upright": "Joy", "reversed": "Pollyannaism"},
    {"card": "Judgement", "upright": "Calling", "reversed": "Criticism"},
    {"card": "The World", "upright": "Completion", "reversed": "Delays"},
    {"card": "Ace of Wands", "upright": "Inspiration", "reversed": "Distractions"},
    {"card": "Two of Wands", "upright": "Planning", "reversed": "Risk Aversion"},
    {"card": "Three of Wands", "upright": "Expansion", "reversed": "Obstacles"},
    {"card": "Four of Wands", "upright": "Celebration", "reversed": "Self-Congratulatory"},
    {"card": "Five of Wands", "upright": "Conflict", "reversed": "Tension"},
    {"card": "Six of Wands", "upright": "Recognition", "reversed": "Ego"},
    {"card": "Seven of Wands", "upright": "Defense", "reversed": "Determination"},
    {"card": "Eight of Wands", "upright": "Speed", "reversed": "Optimal"},
    {"card": "Nine of Wands", "upright": "Persistance", "reversed": "Exhaustion"},
    {"card": "Ten of Wands", "upright": "Responsibility", "reversed": "Burden"},
    {"card": "Page of Wands", "upright": "Potential", "reversed": "Discovery"},
    {"card": "Knight of Wands", "upright": "Energy", "reversed": "Restlessness"},
    {"card": "Queen of Wands", "upright": "Confidence", "reversed": "Actualized"},
    {"card": "King of Wands", "upright": "Leadership", "reversed": "Ruthlessness"},
    {"card": "Ace of Cups", "upright": "Love", "reversed": "Repression"},
    {"card": "Two of Cups", "upright": "Partnership", "reversed": "Distrust"},
    {"card": "Three of Cups", "upright": "Friendship", "reversed": "Independence"},
    {"card": "Four of Cups", "upright": "Meditation", "reversed": "Retreat"},
    {"card": "Five of Cups", "upright": "Regret", "reversed": "Forgiveness"},
    {"card": "Six of Cups", "upright": "Remembrance", "reversed": "Nostalgia"},
    {"card": "Seven of Cups", "upright": "Opportunities", "reversed": "Scrutiny"},
    {"card": "Eight of Cups", "upright": "Departure", "reversed": "Aimlessness"},
    {"card": "Nine of Cups", "upright": "Satisfaction", "reversed": "Indulgence"},
    {"card": "Ten of Cups", "upright": "Fulfillment", "reversed": "Misalignment"},
    {"card": "Page of Cups", "upright": "Imagination", "reversed": "Freshness"},
    {"card": "Knight of Cups", "upright": "Romance", "reversed": "Moodiness"},
    {"card": "Queen of Cups", "upright": "Compassion", "reversed": "Insecurity"},
    {"card": "King of Cups", "upright": "Equanimity", "reversed": "Coldness"},
    {"card": "Ace of Swords", "upright": "Breakthrough", "reversed": "Resilience"},
    {"card": "Two of Swords", "upright": "Evaluation", "reversed": "Paralysis"},
    {"card": "Three of Swords", "upright": "Heartbreak", "reversed": "Catharsis"},
    {"card": "Four of Swords", "upright": "Rest", "reversed": "Burnout"},
    {"card": "Five of Swords", "upright": "Aftermath", "reversed": "Resolution"},
    {"card": "Six of Swords", "upright": "Transition", "reversed": "Departure"},
    {"card": "Seven of Swords", "upright": "Deception", "reversed": "Delusion"},
    {"card": "Eight of Swords", "upright": "Restriction", "reversed": "Reconceptualization"},
    {"card": "Nine of Swords", "upright": "Anxiety", "reversed": "Dilemma"},
    {"card": "Ten of Swords", "upright": "Betrayal", "reversed": "Solace"},
    {"card": "Page of Swords", "upright": "Epistemophilia", "reversed": "Overzealousness"},
    {"card": "Knight of Swords", "upright": "Drive", "reversed": "Impulsiveness"},
    {"card": "Queen of Swords", "upright": "Truth", "reversed": "Bluntness"},
    {"card": "King of Swords", "upright": "Clarity", "reversed": "Influence"},
    {"card": "Ace of Pentacles", "upright": "Prosperity", "reversed": "Missed Opportunity"},
    {"card": "Two of Pentacles", "upright": "Balance", "reversed": "Management"},
    {"card": "Three of Pentacles", "upright": "Collaboration", "reversed": "Understanding"},
    {"card": "Four of Pentacles", "upright": "Conservatism", "reversed": "Greed"},
    {"card": "Five of Pentacles", "upright": "Hardship", "reversed": "Recovery"},
    {"card": "Six of Pentacles", "upright": "Generosity", "reversed": "Exploitation"},
    {"card": "Seven of Pentacles", "upright": "Patience", "reversed": "Immediacy"},
    {"card": "Eight of Pentacles", "upright": "Diligence", "reversed": "Perfectionism"},
    {"card": "Nine of Pentacles", "upright": "Luxury", "reversed": "Maintenance"},
    {"card": "Ten of Pentacles", "upright": "Wealth", "reversed": "Legacy"},
    {"card": "Page of Pentacles", "upright": "Ambition", "reversed": "Manifest"},
    {"card": "Knight of Pentacles", "upright": "Efficiency", "reversed": "Boredom"},
    {"card": "Queen of Pentacles", "upright": "Nurturing", "reversed": "Smothering"},
    {"card": "King of Pentacles", "upright": "Abundance", "reversed": "Materialism"}
  ]
  